Projeto/modulos/alu.v
module alu (clk, readdata1R, readdata2R, alusrc, alucontrol, immediate, aluresult1, aluresult2, pcsrc, branch);
    input wire clk;
    input [31:0] readdata1R;
    input [31:0] readdata2R;
    input alusrc;
    input [11:0] immediate;
    input branch;
    input [3:0] alucontrol;
    output reg [31:0] aluresult1;
    output reg [31:0] aluresult2;
    output reg pcsrc;

    always @(posedge clk) begin
        case (alusrc)
            1'b0: begin // operações para funções que não usam imediato
                case (alucontrol)
                    4'b0010: begin // soma
                        aluresult2 <= readdata1R + readdata2R;
                        aluresult1 <= 1'b0;
                    end
                    4'b0110: begin //subtração
                        aluresult2 <= readdata1R - readdata2R;
                        aluresult1 <= 1'b0;
                    end
                    4'b0010: begin // xor
                        aluresult2 <= readdata1R ^ readdata2R;
                        aluresult1 <= 1'b0;
                    end
                    4'b0101: begin // slr
                        aluresult2 <= readdata1R >>> readdata2R;
                        aluresult1 <= 1'b0;
                    end
                endcase
            end
            1'b1: begin // operações para funções que usam imediato
                case (alucontrol)
                    4'b0010: begin // soma lw e sw
                        aluresult2 <= readdata1R + immediate;
                        aluresult1 <= 1'b0;
                        
                    end
                     4'b0110: begin //subtração para beq
                        aluresult2 <= readdata1R - readdata2R;
                        if(aluresult2 == 0) begin
                            aluresult1 <= 1'b1;
                        end
                    end
                endcase
            end
        endcase
        pcsrc <= aluresult1 & branch;
    end
    
endmodule

Projeto/modulos/registradores.v
module registradores (clk, rs1, rs2, rd, writedataR, readdata1R, readdata2R, regiwrite);
    input wire clk;
    input [4:0] rs1;
    input [4:0] rs2;
    input [4:0] rd;
    input regiwrite;
    input [31:0] writedataR;
    output reg [31:0] readdata1R;
    output reg [31:0] readdata2R;
    reg [31:0] memoriaderegistradores [0:31];

    always @(posedge clk) begin
        readdata1R <= memoriaderegistradores[rs1];
        readdata2R <= memoriaderegistradores[rs2];
        if(regiwrite == 1'b1) begin
            memoriaderegistradores[rd] <= writedataR;
        end
    end
    
endmodule

Projeto/modulos/sinaisdecontrole.v
module sinaisdecontrole (tipo, regiwrite, memwrite, memread, alucontrol, funct3, clk, branch, memtoreg, alusrc);
    input wire [2:0] tipo;
    input wire [2:0] funct3;
    //input wire aluresult1;
    input wire clk;
    output reg regiwrite;
    output reg [1:0] aluop;
    output reg memwrite;
    output reg memread;
    output reg [3:0] alucontrol;
    output reg branch;
    output reg memtoreg;
    output reg alusrc;

    always @(posedge clk)begin
        case (tipo)
            3'b000: begin //lw
                regiwrite <= 1'b1;
                memwrite <= 1'b0;
                memread <= 1'b1;
                alucontrol <= 4'b0010;
                branch <= 1'b0;
                memtoreg <= 1'b1;
                alusrc <= 1'b1;
            end
            3'b010: begin //sw
                regiwrite <= 1'b0;
                memwrite <= 1'b1;
                memread <= 1'b0;
                alucontrol <= 4'b0010;
                branch <= 1'b0;
                memtoreg <= 1'b1;
                alusrc <= 1'b1;
            end
            3'b011: begin
                case (funct3)
                    3'b000 : begin //sub
                        regiwrite <= 1'b1;
                        memwrite <= 1'b0;
                        memread <= 1'b0;
                        alucontrol <= 4'b0110;
                        branch <= 1'b0;
                        memtoreg <= 1'b0;
                        alusrc <= 1'b0;
                    end
                    3'b100 : begin //xor
                        regiwrite <= 1'b1;
                        memwrite <= 1'b0;
                        memread <= 1'b0;
                        alucontrol <= 4'b0010;
                        branch <= 1'b0;
                        memtoreg <= 1'b0;
                        alusrc <= 1'b0;
                    end
                    3'b101 : begin //srl
                        regiwrite <= 1'b1;
                        memwrite <= 1'b0;
                        memread <= 1'b0;
                        alucontrol <= 4'b0101;
                        branch <= 1'b0;
                        memtoreg <= 1'b0;
                        alusrc <= 1'b0;
                    end
                endcase
            end
            3'b110: begin //beq
                regiwrite <= 1'b0;
                memwrite <= 1'b0;
                memread <= 1'b0;
                alucontrol <= 4'b0110;
                branch <= 1'b1;
                memtoreg <= 1'b0;
                alusrc <= 1'b1;
            end
        endcase
    end
    
endmodule

Projeto/modulos/decodificacao.v
module decodificacao (instrucao, opcode, rd, rs1, rs2, funct3, funct7, immediate, tipo, clk);
    //input wire clock,
    input wire [31:0] instrucao;
    input wire clk;
    output reg [6:0] opcode;
    output reg [4:0] rd;
    output reg [4:0] rs1;
    output reg [4:0] rs2;
    output reg [2:0] funct3;
    output reg [6:0] funct7;
    output reg [11:0] immediate; 
    output reg [2:0] tipo;

    always @(posedge clk) begin
    opcode <= instrucao [6:0];
    case (opcode[6:4]) 
      3'b000: begin //formato i
        rd <= instrucao[11:7];
        rs1 <= instrucao[19:15];
        funct3 <= instrucao[14:12];
        immediate <= instrucao[31:20];
        tipo <= 3'b000;
      end
      3'b010: begin //formato s
        immediate <= {instrucao[31:25], instrucao[11:7]};
        rs1 <= instrucao[19:15];
        rs2 <= instrucao[24:20];
        funct3 <= instrucao[14:12];
        tipo <= 3'b010;
      end
      3'b011: begin //formato r
        funct7 <= instrucao[31:25];
        rs2 <= instrucao[24:20];
        rs1 <= instrucao[19:15];
        rd <= instrucao[11:7];
        funct3 <= instrucao[14:12];
        tipo <= 3'b011;
      end 
      3'b110: begin //formato sb
        immediate <= {instrucao[31:25], instrucao[11:7]};
        rs1 <= instrucao[19:15];
        rs2 <= instrucao[24:20];
        funct3 <= instrucao[14:12];
        tipo <= 3'b110;
      end 
    endcase
  end

endmodule

Projeto/modulos/lerinstrucao.v
module lerinstrucao (instrucao, PC, clk);
    input wire [31:0] PC;
    input wire clk;
    output reg [31:0] instrucao;
    reg [31:0] instrucoes [0:6]; // Memória de instruções

    initial begin
        $readmemb("entrada/teste.bin", instrucoes); // Lendo instruções em formato binário
        instrucao <= instrucoes[PC];
    end

    always @(posedge clk) begin
        instrucao <= instrucoes[PC];
    end


endmodule

Projeto/modulos/somapc.v
module somapc (PC, clk, pcsrc, immediate);
  input wire clk;
  input pcsrc;
  input [11:0] immediate;
  output reg [31:0] PC;

  initial begin
      PC <= 0;
  end

  always @(posedge clk) begin
    #10
    case (pcsrc)
        1'b0: PC <= PC + 1;
        1'b1: PC <= PC + immediate;
    endcase
    PC <= PC + 1;
  end

endmodule

Projeto/modulos/clock.v
module clock (clk);
    output reg clk;

    initial begin
        clk = 1'b0;
    end

    // Clock
    always begin
        case (clk)
            1'b0: #1 clk <= 1'b1;
            1'b1: #1 clk <= 1'b0;
        endcase
    end

endmodule

Projeto/main.v
`include "modulos/lerinstrucao.v"
`include "modulos/decodificacao.v"
`include "modulos/sinaisdecontrole.v"
`include "modulos/somapc.v"
`include "modulos/clock.v"
`include "modulos/registradores.v"
`include "modulos/alu.v"

//lw sw sub xor addi srl beq

module main;
    //IF
    wire [31:0] instrucao;
    wire [6:0] opcode;
    wire [4:0] rd;
    wire [4:0] rs1;
    wire [4:0] rs2;
    wire [2:0] funct3;
    wire [6:0] funct7;
    wire [11:0] immediate;
    wire [2:0] tipo;
    wire [31:0] PC;
    wire clk;

    //ID
    wire [31:0] readdata1R; //R para indicar que pertence ao banco de registradores
    wire [31:0] readdata2R; //R para indicar que pertence ao banco de registradores
    wire [31:0] writedataR; //R para indicar que pertence ao banco de registradores

    //EX
    wire [31:0] aluresult1;
    wire [31:0] aluresult2;

    //MEM
    wire [31:0] reddataM; //M para indicar que pertence a memoria

    //sinais de controle
    wire regiwrite;
    wire [3:0] alucontrol;
    wire branch;
    wire memwrite;
    wire memread;
    wire pcsrc;
    wire memtoreg;
    wire alusrc;


    //parametros do estado
    parameter IF = 3'b000, //posição instrução
              ID = 3'b001, //leitura
              EX = 3'b010, //execução
              MEM = 3'b011, //leitura memoria
              WB = 3'b100, //escrita
              FIM = 3'b110; //finish


    // //maquina de estados
    reg [2:0] estado;

    initial begin
        $dumpfile("wavefile.vcd");
        $dumpvars;
        estado <= IF;
    end

    clock clock(.clk(clk));
    somapc somapc(.PC(PC), .clk(clk), .pcsrc(pcsrc), .immediate(immediate));
    lerinstrucao lerinstrucao(.instrucao(instrucao), .PC(PC), .clk(clk));
    decodificacao decodificacao(.instrucao(instrucao), .opcode(opcode), .rd(rd), .rs1(rs1), .rs2(rs2), .funct3(funct3), .funct7(funct7), .immediate(immediate), .tipo(tipo), .clk(clk));
    sinaisdecontrole sinaisdecontrole(.tipo(tipo), .regiwrite(regiwrite), .memwrite(memwrite), .memread(memread), .alucontrol(alucontrol), .funct3(funct3), .clk(clk), .branch(branch), .memtoreg(memtoreg), .alusrc(alusrc));
    registradores registradores(.clk(clk), .rs1(rs1), .rs2(rs2), .rd(rd), .writedataR(writedataR), .readdata1R(readdata1R), .readdata2R(readdata2R), .regiwrite(regiwrite));
    alu alu(.clk(clk), .readdata1R(readdata1R), .readdata2R(readdata2R), .alusrc(alusrc), .alucontrol(alucontrol), .immediate(immediate), .aluresult1(aluresult1), .aluresult2(aluresult2), .pcsrc(pcsrc), .branch(branch));


    always @(posedge clk) begin
        case(estado)
        IF : begin
            estado <= ID;
        end
        ID: begin
            if(PC < 7) begin
                estado <= IF;
            end
            else begin
                estado <= FIM;
            end
        end
        FIM : begin
            $finish;
        end
        endcase
     
    end


endmodule

Projeto/wavefile.vcd
$date
	Tue May 30 11:07:14 2023
$end
$version
	Icarus Verilog
$end
$timescale
	1s
$end
$scope module main $end
$var wire 32 ! writedataR [31:0] $end
$var wire 3 " tipo [2:0] $end
$var wire 5 # rs2 [4:0] $end
$var wire 5 $ rs1 [4:0] $end
$var wire 1 % regiwrite $end
$var wire 32 & readdata2R [31:0] $end
$var wire 32 ' readdata1R [31:0] $end
$var wire 5 ( rd [4:0] $end
$var wire 1 ) pcsrc $end
$var wire 7 * opcode [6:0] $end
$var wire 1 + memwrite $end
$var wire 1 , memtoreg $end
$var wire 1 - memread $end
$var wire 32 . instrucao [31:0] $end
$var wire 12 / immediate [11:0] $end
$var wire 7 0 funct7 [6:0] $end
$var wire 3 1 funct3 [2:0] $end
$var wire 1 2 clk $end
$var wire 1 3 branch $end
$var wire 1 4 alusrc $end
$var wire 32 5 aluresult2 [31:0] $end
$var wire 32 6 aluresult1 [31:0] $end
$var wire 4 7 alucontrol [3:0] $end
$var wire 32 8 PC [31:0] $end
$var reg 3 9 estado [2:0] $end
$scope module alu $end
$var wire 32 : readdata2R [31:0] $end
$var wire 32 ; readdata1R [31:0] $end
$var wire 12 < immediate [11:0] $end
$var wire 1 2 clk $end
$var wire 1 3 branch $end
$var wire 1 4 alusrc $end
$var wire 4 = alucontrol [3:0] $end
$var reg 32 > aluresult1 [31:0] $end
$var reg 32 ? aluresult2 [31:0] $end
$var reg 1 ) pcsrc $end
$upscope $end
$scope module clock $end
$var reg 1 2 clk $end
$upscope $end
$scope module decodificacao $end
$var wire 1 2 clk $end
$var wire 32 @ instrucao [31:0] $end
$var reg 3 A funct3 [2:0] $end
$var reg 7 B funct7 [6:0] $end
$var reg 12 C immediate [11:0] $end
$var reg 7 D opcode [6:0] $end
$var reg 5 E rd [4:0] $end
$var reg 5 F rs1 [4:0] $end
$var reg 5 G rs2 [4:0] $end
$var reg 3 H tipo [2:0] $end
$upscope $end
$scope module lerinstrucao $end
$var wire 1 2 clk $end
$var wire 32 I PC [31:0] $end
$var reg 32 J instrucao [31:0] $end
$upscope $end
$scope module registradores $end
$var wire 1 2 clk $end
$var wire 5 K rd [4:0] $end
$var wire 5 L rs1 [4:0] $end
$var wire 5 M rs2 [4:0] $end
$var wire 32 N writedataR [31:0] $end
$var wire 1 % regiwrite $end
$var reg 32 O readdata1R [31:0] $end
$var reg 32 P readdata2R [31:0] $end
$upscope $end
$scope module sinaisdecontrole $end
$var wire 1 2 clk $end
$var wire 3 Q funct3 [2:0] $end
$var wire 3 R tipo [2:0] $end
$var reg 4 S alucontrol [3:0] $end
$var reg 2 T aluop [1:0] $end
$var reg 1 4 alusrc $end
$var reg 1 3 branch $end
$var reg 1 - memread $end
$var reg 1 , memtoreg $end
$var reg 1 + memwrite $end
$var reg 1 % regiwrite $end
$upscope $end
$scope module somapc $end
$var wire 1 2 clk $end
$var wire 12 U immediate [11:0] $end
$var wire 1 ) pcsrc $end
$var reg 32 V PC [31:0] $end
$upscope $end
$upscope $end
$enddefinitions $end
#0
$dumpvars
b0 V
bx U
bx T
bx S
bx R
bx Q
bx P
bx O
bz N
bx M
bx L
bx K
bx J
b0 I
bx H
bx G
bx F
bx E
bx D
bx C
bx B
bx A
bx @
bx ?
bx >
bx =
bx <
bx ;
bx :
b0 9
b0 8
bx 7
bx 6
bx 5
x4
x3
02
bx 1
bx 0
bx /
bx .
x-
x,
x+
bx *
x)
bx (
bx '
bx &
x%
bx $
bx #
bx "
bz !
$end
#1
b1 8
b1 I
b1 V
b110000011010000010000011 .
b110000011010000010000011 @
b110000011010000010000011 J
b1 9
12
#3
02
#5
b0 9
b11 *
b11 D
b100011010011000100011 .
b100011010011000100011 @
b100011010011000100011 J
b10 8
b10 I
b10 V
12
#7
02
#9
b11 8
b11 I
b11 V
b1000000011000110000001010110011 .
b1000000011000110000001010110011 @
b1000000011000110000001010110011 J
b0 "
b0 H
b0 R
b1 /
b1 <
b1 C
b1 U
b10 1
b10 A
b10 Q
b11 $
b11 F
b11 L
b1100 (
b1100 E
b1100 K
b100011 *
b100011 D
b1 9
12
#11
02
#13
b0 9
14
1,
03
b10 7
b10 =
b10 S
1-
0+
1%
b10 "
b10 H
b10 R
b0 1
b0 A
b0 Q
b110 #
b110 G
b110 M
b110 $
b110 F
b110 L
b10000000101 /
b10000000101 <
b10000000101 C
b10000000101 U
b110011 *
b110011 D
b10100101100001010110011 .
b10100101100001010110011 @
b10100101100001010110011 J
b100 8
b100 I
b100 V
12
#15
02
#17
b101 8
b101 I
b101 V
b101000011000000110010011 .
b101000011000000110010011 @
b101000011000000110010011 J
b11 "
b11 H
b11 R
b100 1
b100 A
b100 Q
b101 (
b101 E
b101 K
b101 $
b101 F
b101 L
b101 #
b101 G
b101 M
b0 0
b0 B
0-
1+
0%
0)
b0 6
b0 >
b1 9
12
#19
02
#21
b0 9
04
0,
0+
1%
b0 1
b0 A
b0 Q
b11 (
b11 E
b11 K
b11 $
b11 F
b11 L
b1010 #
b1010 G
b1010 M
b10011 *
b10011 D
b1100110101000110110011 .
b1100110101000110110011 @
b1100110101000110110011 J
b110 8
b110 I
b110 V
12
#23
02
#25
b111 8
b111 I
b111 V
b11111110010100011000100011100011 .
b11111110010100011000100011100011 @
b11111110010100011000100011100011 J
b110011 *
b110011 D
b110 7
b110 =
b110 S
b1 9
12
#27
02
#29
b110 9
bz '
bz ;
bz O
b10001 (
b10001 E
b10001 K
b101 #
b101 G
b101 M
b1111111 0
b1111111 B
b1100011 *
b1100011 D
bx .
bx @
bx J
b1000 8
b1000 I
b1000 V
12
#31
02
#33
b1001 8
b1001 I
b1001 V
b110 "
b110 H
b110 R
bx 1
bx A
bx Q
bx #
bx G
bx M
bx $
bx F
bx L
bx /
bx <
bx C
bx U
bx *
bx D
12
