Projeto/control.v
module controle (tipo, regiwrite, aluop, memwrite, memread, alucontrol, funct3, aluresult1, clk);
    input wire [2:0] tipo;
    input wire [2:0] funct3;
    input wire aluresult1;
    input wire clk;
    output reg regiwrite;
    output reg [1:0] aluop;
    output reg memwrite;
    output reg memread;
    output reg [3:0] alucontrol;

    always @(posedge clk or negedge clk)begin
        case (tipo)
            3'b000: begin //lw
                regiwrite <= 1'b1;
                aluop <= 2'b00;
                memwrite <= 1'b0;
                memread <= 1'b1;
                alucontrol <= 4'b0010;
            end
            3'b010: begin //sw
                regiwrite <= 1'b0;
                aluop <= 2'b00;
                memwrite <= 1'b1;
                memread <= 1'b0;
                alucontrol <= 4'b0010;
            end
            3'b011: begin
                case (funct3)
                    3'b000 : begin //sub
                        regiwrite <= 1'b1;
                        aluop <= 2'b10;
                        memwrite <= 1'b0;
                        memread <= 1'b0;
                        alucontrol <= 4'b0110;
                    end
                    3'b100 : begin //xor
                        regiwrite <= 1'b1;
                        aluop <= 2'b10;
                        memwrite <= 1'b0;
                        memread <= 1'b0;
                        alucontrol <= 4'b0010;
                    end
                    3'b101 : begin //srl
                        regiwrite <= 1'b1;
                        aluop <= 2'b10;
                        memwrite <= 1'b0;
                        memread <= 1'b0;
                        alucontrol <= 4'b0101;
                    end
                endcase
            end
            3'b110: begin //beq
                regiwrite <= 1'b0;
                aluop <= 2'b01;
                memwrite <= 1'b0;
                memread <= 1'b0;
                alucontrol <= 4'b0110;
            end
        endcase
    end
    
endmodule

Projeto/decodificacao.v
module decod (instrucao, opcode, rd, rs1, rs2, funct3, funct7, immediate, tipo, clk);
    //input wire clock,
    input wire [31:0] instrucao;
    input wire clk;
    output reg [6:0] opcode;
    output reg [4:0] rd;
    output reg [4:0] rs1;
    output reg [4:0] rs2;
    output reg [2:0] funct3;
    output reg [6:0] funct7;
    output reg [11:0] immediate; 
    output reg [2:0] tipo;

    always @(posedge clk or negedge clk) begin
    opcode <= instrucao [6:0];
    case (opcode[6:4]) 
      3'b000: begin //formato i
        rd <= instrucao[11:7];
        rs1 <= instrucao[19:15];
        funct3 <= instrucao[14:12];
        immediate <= instrucao[31:20];
        tipo <= 3'b000;
      end
      3'b010: begin //formato s
        immediate <= {instrucao[31:25], instrucao[11:7]};
        rs1 <= instrucao[19:15];
        rs2 <= instrucao[24:20];
        funct3 <= instrucao[14:12];
        tipo <= 3'b010;
      end
      3'b011: begin //formato r
        funct7 <= instrucao[31:25];
        rs2 <= instrucao[24:20];
        rs1 <= instrucao[19:15];
        rd <= instrucao[11:7];
        funct3 <= instrucao[14:12];
        tipo <= 3'b011;
      end 
      3'b110: begin //formato sb
        immediate <= {instrucao[31:25], instrucao[11:7]};
        rs1 <= instrucao[19:15];
        rs2 <= instrucao[24:20];
        funct3 <= instrucao[14:12];
        tipo <= 3'b110;
      end 
    endcase
  end

endmodule

Projeto/LerInstrucoes.v
module ler (instrucao, PC, clk);
    input wire [31:0] PC;
    input wire clk;
    output reg [31:0] instrucao;
    reg [31:0] memory [0:6];

    initial begin
        $readmemb("assembler.bin", memory); // Lendo instruções em formato binário
        //$display("Instrucao %0d: %b", i+1, memory[i]);
        instrucao <= memory[PC];
    end

    always @(posedge clk) begin
        instrucao <= memory[PC];
    end


endmodule

Projeto/pc.v
module calcpc (PC, clk);
  input wire clk;
  output reg [31:0] PC;

  initial begin
      PC <= 0;
  end

  always @(posedge clk) begin
      PC <= PC + 1;
  end

endmodule

Projeto/clock.v
module geraclock (clk);
    output reg clk;

    initial begin
        clk = 1'b0;
    end

    always begin
        case (clk)
            1'b0: #1 clk <= 1'b1;
            1'b1: #1 clk <= 1'b0;
        endcase
    end

endmodule

Projeto/teste.v
`include "LerInstrucoes.v"
`include "decodificacao.v"
`include "control.v"
`include "pc.v"
`include "clock.v"

//lw sw sub xor addi srl beq

module teste;
    wire [31:0] instrucao;
    wire [6:0] opcode;
    wire [4:0] rd;
    wire [4:0] rs1;
    wire [4:0] rs2;
    wire [2:0] funct3;
    wire [6:0] funct7;
    wire [11:0] immediate;
    wire [2:0] tipo;
    wire [31:0] PC;
    wire clk;

    //sinais de controle
    wire regiwrite;
    wire [1:0] aluop;
    wire [3:0] alucontrol;
    wire branch;
    wire memwrite;
    wire memread;
    wire aluresult1;
    wire aluresult2;
    

    //parametros do estado
    parameter IF = 3'b000, //posição instrução
              ID = 3'b001, //leitura
              EX = 3'b010, //execução
              MEM = 3'b011, //leitura memoria
              WB = 3'b100, //escrita
              FIM = 3'b110; //finish


    // //maquina de estados
    reg [2:0] estado;

    initial begin
        $dumpfile("waveform.vcd");
        $dumpvars;
        

        estado <= IF;
    end

    geraclock geraclk(.clk(clk));
    calcpc resultpc(.PC(PC), .clk(clk));
    ler leitura(.instrucao(instrucao), .PC(PC), .clk(clk));
    decod decodificar(.instrucao(instrucao), .opcode(opcode), .rd(rd), .rs1(rs1), .rs2(rs2), .funct3(funct3), .funct7(funct7), .immediate(immediate), .tipo(tipo), .clk(clk));
    controle controlador(.tipo(tipo), .regiwrite(regiwrite), .aluop(aluop), .memwrite(memwrite), .memread(memread), .alucontrol(alucontrol), .funct3(funct3), .aluresult1(aluresult1), .clk(clk));

    always @(posedge clk or negedge clk) begin
        case(estado)
        IF : begin
            $display("Instrucao : %b", instrucao);
            estado <= ID;
        end
        ID: begin
            case (tipo)
            3'b000 : $display("formato i");
            3'b010 : $display("formato s");
            3'b011 : $display("formato r");
            3'b110 : $display("formato sb");
            endcase
            #1
            $display("sinal de controle");
            $display("regiwrite : %b", regiwrite);
            $display("aluop : %b", aluop);
            $display("memwrite : %b", memwrite);
            $display("memread : %b", memread);
            $display("alucontrol : %b", alucontrol);
            $display("funct3 : %b", funct3);
            $display("aluresult1 : %b", aluresult1);
            $display("PC: %d", PC);
            if(PC < 7) begin
                estado <= IF;
            end
            else begin
                estado <= FIM;
            end
        end
        FIM : begin
            $finish;
        end
        endcase
     
    end


endmodule

Projeto/waveform.vcd
$date
	Mon May 29 18:12:43 2023
$end
$version
	Icarus Verilog
$end
$timescale
	1s
$end
$scope module teste $end
$var wire 1 ! aluresult1 $end
$var wire 3 " tipo [2:0] $end
$var wire 5 # rs2 [4:0] $end
$var wire 5 $ rs1 [4:0] $end
$var wire 1 % regiwrite $end
$var wire 5 & rd [4:0] $end
$var wire 7 ' opcode [6:0] $end
$var wire 1 ( memwrite $end
$var wire 1 ) memread $end
$var wire 32 * instrucao [31:0] $end
$var wire 12 + immediate [11:0] $end
$var wire 7 , funct7 [6:0] $end
$var wire 3 - funct3 [2:0] $end
$var wire 1 . clk $end
$var wire 2 / aluop [1:0] $end
$var wire 4 0 alucontrol [3:0] $end
$var wire 32 1 PC [31:0] $end
$var reg 3 2 estado [2:0] $end
$scope module controlador $end
$var wire 1 ! aluresult1 $end
$var wire 3 3 tipo [2:0] $end
$var wire 3 4 funct3 [2:0] $end
$var wire 1 . clk $end
$var reg 4 5 alucontrol [3:0] $end
$var reg 2 6 aluop [1:0] $end
$var reg 1 ) memread $end
$var reg 1 ( memwrite $end
$var reg 1 % regiwrite $end
$upscope $end
$scope module decodificar $end
$var wire 32 7 instrucao [31:0] $end
$var wire 1 . clk $end
$var reg 3 8 funct3 [2:0] $end
$var reg 7 9 funct7 [6:0] $end
$var reg 12 : immediate [11:0] $end
$var reg 7 ; opcode [6:0] $end
$var reg 5 < rd [4:0] $end
$var reg 5 = rs1 [4:0] $end
$var reg 5 > rs2 [4:0] $end
$var reg 3 ? tipo [2:0] $end
$upscope $end
$scope module geraclk $end
$var reg 1 . clk $end
$upscope $end
$scope module leitura $end
$var wire 1 . clk $end
$var wire 32 @ PC [31:0] $end
$var reg 32 A instrucao [31:0] $end
$upscope $end
$scope module resultpc $end
$var wire 1 . clk $end
$var reg 32 B PC [31:0] $end
$upscope $end
$upscope $end
$enddefinitions $end
#0
$dumpvars
b0 B
bx A
b0 @
bx ?
bx >
bx =
bx <
bx ;
bx :
bx 9
bx 8
bx 7
bx 6
bx 5
bx 4
bx 3
b0 2
b0 1
bx 0
bx /
0.
bx -
bx ,
bx +
bx *
x)
x(
bx '
bx &
x%
bx $
bx #
bx "
z!
$end
#1
b1 2
b1 1
b1 @
b1 B
b110000011010000010000011 *
b110000011010000010000011 7
b110000011010000010000011 A
1.
#3
b11 '
b11 ;
0.
#4
b0 2
#5
b0 "
b0 3
b0 ?
b1100 +
b1100 :
b10 -
b10 4
b10 8
b11 $
b11 =
b1 &
b1 <
b1 2
b100011010011000100011 *
b100011010011000100011 7
b100011010011000100011 A
b10 1
b10 @
b10 B
1.
#7
b10 0
b10 5
1)
0(
b0 /
b0 6
1%
b1 +
b1 :
b1100 &
b1100 <
b100011 '
b100011 ;
0.
#8
b0 2
#9
b10 "
b10 3
b10 ?
b1 #
b1 >
b1100 +
b1100 :
b1 2
b11 1
b11 @
b11 B
b1000000011000110000001010110011 *
b1000000011000110000001010110011 7
b1000000011000110000001010110011 A
1.
#11
0)
1(
0%
b0 -
b0 4
b0 8
b110 #
b110 >
b110 $
b110 =
b10000000101 +
b10000000101 :
b110011 '
b110011 ;
0.
#12
b0 2
#13
b11 "
b11 3
b11 ?
b101 &
b101 <
b100000 ,
b100000 9
b1 2
b10100101100001010110011 *
b10100101100001010110011 7
b10100101100001010110011 A
b100 1
b100 @
b100 B
1.
#15
b110 0
b110 5
0(
b10 /
b10 6
1%
b100 -
b100 4
b100 8
b101 $
b101 =
b101 #
b101 >
b0 ,
b0 9
0.
#16
b0 2
#17
b10 0
b10 5
b1 2
b101 1
b101 @
b101 B
b101000011000000110010011 *
b101000011000000110010011 7
b101000011000000110010011 A
1.
#19
b0 -
b0 4
b0 8
b11 &
b11 <
b11 $
b11 =
b1010 #
b1010 >
b10011 '
b10011 ;
0.
#20
b0 2
#21
b110 0
b110 5
b1 2
b1100110101000110110011 *
b1100110101000110110011 7
b1100110101000110110011 A
b110 1
b110 @
b110 B
1.
#23
b110011 '
b110011 ;
0.
#24
b0 2
#25
b101 -
b101 4
b101 8
b110 $
b110 =
b11 #
b11 >
b1 2
b111 1
b111 @
b111 B
b11111110010100011000100011100011 *
b11111110010100011000100011100011 7
b11111110010100011000100011100011 A
1.
#27
b101 0
b101 5
b0 -
b0 4
b0 8
b10001 &
b10001 <
b11 $
b11 =
b101 #
b101 >
b1111111 ,
b1111111 9
b1100011 '
b1100011 ;
0.
#28
b110 2
#29
b110 "
b110 3
b110 ?
b111111110001 +
b111111110001 :
b110 0
b110 5
bx *
bx 7
bx A
b1000 1
b1000 @
b1000 B
1.
