Projeto/modulos/memoria.v
module memoria (clk, aluresult2, rs2, reddataM, memwrite, memread, immediate, mem0, mem1, mem2, mem3, mem4, mem5, mem6, mem7, mem8, mem9, mem10, mem11, mem12, mem13, mem14, mem15, mem16, mem17, mem18, mem19, mem20, mem21, mem22, mem23, mem24, mem25, mem26, mem27, mem28, mem29, mem30, mem31);
    input wire clk;
    input [31:0] aluresult2;
    input [4:0] rs2;
    input memwrite;
    input memread;
    input [11:0] immediate;
    output reg [31:0] reddataM;
    output reg [31:0] mem0, mem1, mem2, mem3, mem4, mem5, mem6, mem7, mem8, mem9, mem10, mem11;
    output reg [31:0] mem12, mem13, mem14, mem15, mem16, mem17, mem18, mem19, mem20, mem21, mem22, mem23; 
    output reg [31:0] mem24, mem25, mem26, mem27, mem28, mem29, mem30, mem31;
    //reg [31:0] immediateaux;
    reg [31:0] memoria [0:31];

    initial begin
        $readmemb("entrada/memoria.bin", memoria); // iniciando a memoria
        mem0 <= memoria[0];
        mem1 <= memoria[1];
        mem2 <= memoria[2];
        mem3 <= memoria[3];
        mem4 <= memoria[4];
        mem5 <= memoria[5];
        mem6 <= memoria[6];
        mem7 <= memoria[7];
        mem8 <= memoria[8];
        mem9 <= memoria[9];
        mem10 <= memoria[10];
        mem11 <= memoria[11];
        mem12 <= memoria[12];
        mem13 <= memoria[13];
        mem14 <= memoria[14];
        mem15 <= memoria[15];
        mem16 <= memoria[16];
        mem17 <= memoria[17];
        mem18 <= memoria[18];
        mem19 <= memoria[19];
        mem20 <= memoria[20];
        mem21 <= memoria[21];
        mem22 <= memoria[22];
        mem23 <= memoria[23];
        mem24 <= memoria[24];
        mem25 <= memoria[25];
        mem26 <= memoria[26];
        mem27 <= memoria[27];
        mem28 <= memoria[28];
        mem29 <= memoria[29];
        mem30 <= memoria[30];
        mem31 <= memoria[31];
    end

    always @(posedge clk) begin
        //immediateaux <= immediate / 4;
        if(memwrite == 1'b1) begin
            memoria[aluresult2] <= rs2;
        end
        if(memread == 1'b1) begin
            reddataM <= memoria[aluresult2];
        end
        mem0 <= memoria[0];
        mem1 <= memoria[1];
        mem2 <= memoria[2];
        mem3 <= memoria[3];
        mem4 <= memoria[4];
        mem5 <= memoria[5];
        mem6 <= memoria[6];
        mem7 <= memoria[7];
        mem8 <= memoria[8];
        mem9 <= memoria[9];
        mem10 <= memoria[10];
        mem11 <= memoria[11];
        mem12 <= memoria[12];
        mem13 <= memoria[13];
        mem14 <= memoria[14];
        mem15 <= memoria[15];
        mem16 <= memoria[16];
        mem17 <= memoria[17];
        mem18 <= memoria[18];
        mem19 <= memoria[19];
        mem20 <= memoria[20];
        mem21 <= memoria[21];
        mem22 <= memoria[22];
        mem23 <= memoria[23];
        mem24 <= memoria[24];
        mem25 <= memoria[25];
        mem26 <= memoria[26];
        mem27 <= memoria[27];
        mem28 <= memoria[28];
        mem29 <= memoria[29];
        mem30 <= memoria[30];
        mem31 <= memoria[31];
    end
    
endmodule

Projeto/modulos/alu.v
module alu (clk, readdata1R, readdata2R, alusrc, alucontrol, immediate, aluresult1, aluresult2, pcsrc, branch);
    input wire clk;
    input [31:0] readdata1R;
    input [31:0] readdata2R;
    input alusrc;
    input [11:0] immediate;
    input branch;
    output reg [31:0] aluresult1;
    output reg [31:0] aluresult2;
    output reg pcsrc;

    always @(posedge clk) begin
        case (alusrc)
            1'b0: begin // operações para funções que não usam imediato
                case (alucontrol)
                    4'b0010: begin // soma
                        aluresult2 <= readdata1R + readdata2R;
                        writedataR <= aluresult2;
                        aluresult1 <= 1'b0;
                    end
                    4'b0110: begin //subtração
                        aluresult2 <= readdata1R - readdata2R;
                        writedataR <= aluresult2;
                        aluresult1 <= 1'b0;
                    end
                    4'b0010: begin // xor
                        aluresult2 <= readdata1R ^ readdata2R;
                        writedataR <= aluresult2;
                        aluresult1 <= 1'b0;
                    end
                    4'b0101: begin // slr
                        aluresult2 <= readdata1R >>> readdata2R;
                        writedataR <= aluresult2;
                        aluresult1 <= 1'b0;
                    end
                endcase
            end
            1'b1: begin // operações para funções que usam imediato
                case (alucontrol)
                    4'b0010: begin // soma lw e sw
                        aluresult2 <= readdata1R + imediato;
                        writedataR <= aluresult1;
                        aluresult1 <= 1'b0;
                    end
                     4'b0110: begin //subtração para beq
                        aluresult2 <= readdata1R - readdata2R;
                        writedataR <= aluresult2;
                        if(aluresult2 == 0) begin
                            aluresult1 <= 1'b1;
                        end
                    end
                endcase
            end
        endcase
        pcsrc <= aluresult1 & branch;
    end
    
endmodule

Projeto/modulos/registradores.v
module registradores (clk, rs1, rs2, rd, readdata1R, readdata2R, regiwrite, memtoreg, aluresult2, reddataM, reg0, reg1, reg2, reg3, reg4, reg5, reg6, reg7, reg8, reg9, reg10, reg11, reg12, reg13, reg14, reg15, reg16, reg17, reg18, reg19, reg20, reg21, reg22, reg23, reg24, reg25, reg26, reg27, reg28, reg29, reg30, reg31);
    input wire clk;
    input [4:0] rs1;
    input [4:0] rs2;
    input [4:0] rd;
    input regiwrite;
    input memtoreg;
    input [31:0] aluresult2;
    input [31:0] reddataM;
    output reg [31:0] readdata1R;
    output reg [31:0] readdata2R;
    output reg [31:0] reg0, reg1, reg2, reg3, reg4, reg5, reg6, reg7, reg8, reg9, reg10, reg11;
    output reg [31:0] reg12, reg13, reg14, reg15, reg16, reg17, reg18, reg19, reg20, reg21, reg22, reg23; 
    output reg [31:0] reg24, reg25, reg26, reg27, reg28, reg29, reg30, reg31;
    reg [31:0] bancoregistradores [0:31];

    initial begin
        $readmemb("entrada/registradores.bin", bancoregistradores); // Lendo registradores
    end

    always @(posedge clk) begin
        readdata1R <= bancoregistradores[rs1];
        readdata2R <= bancoregistradores[rs2];
        case (regiwrite)
            1'b1: begin
                case (memtoreg)
                    1'b1: begin
                        bancoregistradores[rd] <= reddataM;
                    end
                    1'b0: begin
                        bancoregistradores[rd] <= aluresult2;
                    end
                endcase
            end 
        endcase
        reg0 <= bancoregistradores[0];
        reg1 <= bancoregistradores[1];
        reg2 <= bancoregistradores[2];
        reg3 <= bancoregistradores[3];
        reg4 <= bancoregistradores[4];
        reg5 <= bancoregistradores[5];
        reg6 <= bancoregistradores[6];
        reg7 <= bancoregistradores[7];
        reg8 <= bancoregistradores[8];
        reg9 <= bancoregistradores[9];
        reg10 <= bancoregistradores[10];
        reg11 <= bancoregistradores[11];
        reg12 <= bancoregistradores[12];
        reg13 <= bancoregistradores[13];
        reg14 <= bancoregistradores[14];
        reg15 <= bancoregistradores[15];
        reg16 <= bancoregistradores[16];
        reg17 <= bancoregistradores[17];
        reg18 <= bancoregistradores[18];
        reg19 <= bancoregistradores[19];
        reg20 <= bancoregistradores[20];
        reg21 <= bancoregistradores[21];
        reg22 <= bancoregistradores[22];
        reg23 <= bancoregistradores[23];
        reg24 <= bancoregistradores[24];
        reg25 <= bancoregistradores[25];
        reg26 <= bancoregistradores[26];
        reg27 <= bancoregistradores[27];
        reg28 <= bancoregistradores[28];
        reg29 <= bancoregistradores[29];
        reg30 <= bancoregistradores[30];
        reg31 <= bancoregistradores[31];
    end
    
endmodule

Projeto/modulos/sinaisdecontrole.v
module sinaisdecontrole (tipo, regiwrite, memwrite, memread, alucontrol, funct3, clk, branch, memtoreg, alusrc);
    input wire [2:0] tipo;
    input wire [2:0] funct3;
    //input wire aluresult1;
    input wire clk;
    output reg regiwrite;
    output reg [1:0] aluop;
    output reg memwrite;
    output reg memread;
    output reg [3:0] alucontrol;
    output reg branch;
    output reg memtoreg;
    output reg alusrc;

    always @(posedge clk)begin
        case (tipo)
            3'b000: begin //lw
                regiwrite <= 1'b1;
                memwrite <= 1'b0;
                memread <= 1'b1;
                alucontrol <= 4'b0010;
                branch <= 1'b0;
                memtoreg <= 1'b1;
                alusrc <= 1'b1;
            end
            3'b010: begin //sw
                regiwrite <= 1'b0;
                memwrite <= 1'b1;
                memread <= 1'b0;
                alucontrol <= 4'b0010;
                branch <= 1'b0;
                memtoreg <= 1'b1;
                alusrc <= 1'b1;
            end
            3'b011: begin
                case (funct3)
                    3'b000 : begin //sub
                        regiwrite <= 1'b1;
                        memwrite <= 1'b0;
                        memread <= 1'b0;
                        alucontrol <= 4'b0110;
                        branch <= 1'b0;
                        memtoreg <= 1'b0;
                        alusrc <= 1'b0;
                    end
                    3'b100 : begin //xor
                        regiwrite <= 1'b1;
                        memwrite <= 1'b0;
                        memread <= 1'b0;
                        alucontrol <= 4'b0010;
                        branch <= 1'b0;
                        memtoreg <= 1'b0;
                        alusrc <= 1'b0;
                    end
                    3'b101 : begin //srl
                        regiwrite <= 1'b1;
                        memwrite <= 1'b0;
                        memread <= 1'b0;
                        alucontrol <= 4'b0101;
                        branch <= 1'b0;
                        memtoreg <= 1'b0;
                        alusrc <= 1'b0;
                    end
                endcase
            end
            3'b110: begin //beq
                regiwrite <= 1'b0;
                memwrite <= 1'b0;
                memread <= 1'b0;
                alucontrol <= 4'b0110;
                branch <= 1'b1;
                memtoreg <= 1'b0;
                alusrc <= 1'b1;
            end
        endcase
    end
    
endmodule

Projeto/modulos/decodificacao.v
module decodificacao (instrucao, opcode, rd, rs1, rs2, funct3, funct7, immediate, tipo, clk);
    //input wire clock,
    input wire [31:0] instrucao;
    input wire clk;
    output reg [6:0] opcode;
    output reg [4:0] rd;
    output reg [4:0] rs1;
    output reg [4:0] rs2;
    output reg [2:0] funct3;
    output reg [6:0] funct7;
    output reg [11:0] immediate; 
    output reg [2:0] tipo;

    always @(posedge clk) begin
    opcode <= instrucao [6:0];
    case (opcode[6:4]) 
      3'b000: begin //formato i
        rd <= instrucao[11:7];
        rs1 <= instrucao[19:15];
        funct3 <= instrucao[14:12];
        immediate <= instrucao[31:20];
        tipo <= 3'b000;
      end
      3'b010: begin //formato s
        immediate <= {instrucao[31:25], instrucao[11:7]};
        rs1 <= instrucao[19:15];
        rs2 <= instrucao[24:20];
        funct3 <= instrucao[14:12];
        tipo <= 3'b010;
      end
      3'b011: begin //formato r
        funct7 <= instrucao[31:25];
        rs2 <= instrucao[24:20];
        rs1 <= instrucao[19:15];
        rd <= instrucao[11:7];
        funct3 <= instrucao[14:12];
        tipo <= 3'b011;
      end 
      3'b110: begin //formato sb
        immediate <= {instrucao[31:25], instrucao[11:7]};
        rs1 <= instrucao[19:15];
        rs2 <= instrucao[24:20];
        funct3 <= instrucao[14:12];
        tipo <= 3'b110;
      end 
    endcase
  end

endmodule

Projeto/modulos/lerinstrucao.v
module lerinstrucao (instrucao, PC, clk);
    input wire [31:0] PC;
    input wire clk;
    output reg [31:0] instrucao;
    reg [31:0] instrucoes [0:6]; // Memória de instruções

    initial begin
        $readmemb("entrada/assembler.bin", instrucoes); // Lendo instruções em formato binário
        instrucao <= instrucoes[PC];
    end

    always @(posedge clk) begin
        #10
        instrucao <= instrucoes[PC];
    end


endmodule

Projeto/modulos/somapc.v
module somapc (PC, clk, pcsrc, immediate);
  input wire clk;
  input pcsrc;
  input [11:0] immediate;
  output reg [31:0] PC;

  initial begin
      PC <= 0;
  end

  always @(posedge clk) begin
    #10
    case (pcsrc)
        1'b0: PC <= PC + 1;
        1'b1: PC <= PC + immediate;
    endcase
    PC <= PC + 1;
  end

endmodule

Projeto/modulos/clock.v
module clock (clk);
    output reg clk;

    initial begin
        clk = 1'b0;
    end

    // Clock
    always begin
        case (clk)
            1'b0: #1 clk <= 1'b1;
            1'b1: #1 clk <= 1'b0;
        endcase
    end

endmodule

Projeto/main.v
`include "modulos/lerinstrucao.v"
`include "modulos/decodificacao.v"
`include "modulos/sinaisdecontrole.v"
`include "modulos/somapc.v"
`include "modulos/clock.v"
`include "modulos/registradores.v"
`include "modulos/alu.v"
`include "modulos/memoria.v"

//lw sw sub xor addi srl beq

module main;
    //IF
    wire [31:0] instrucao;
    wire [6:0] opcode;
    wire [4:0] rd;
    wire [4:0] rs1;
    wire [4:0] rs2;
    wire [2:0] funct3;
    wire [6:0] funct7;
    wire [11:0] immediate;
    wire [2:0] tipo;
    wire [31:0] PC;
    wire clk;

    //ID
    wire [31:0] readdata1R; //R para indicar que pertence ao banco de registradores
    wire [31:0] readdata2R; //R para indicar que pertence ao banco de registradores
    wire [31:0] reg0, reg1, reg2, reg3, reg4, reg5, reg6, reg7, reg8, reg9, reg10, reg11;
    wire [31:0] reg12, reg13, reg14, reg15, reg16, reg17, reg18, reg19, reg20, reg21, reg22, reg23; 
    wire [31:0] reg24, reg25, reg26, reg27, reg28, reg29, reg30, reg31;

    //EX
    wire [31:0] aluresult1;
    wire [31:0] aluresult2;

    //MEM
    wire [31:0] reddataM; //M para indicar que pertence a memoria
    wire [31:0] mem0, mem1, mem2, mem3, mem4, mem5, mem6, mem7, mem8, mem9, mem10, mem11;
    wire [31:0] mem12, mem13, mem14, mem15, mem16, mem17, mem18, mem19, mem20, mem21, mem22, mem23; 
    wire [31:0] mem24, mem25, mem26, mem27, mem28, mem29, mem30, mem31;

    //sinais de controle
    wire regiwrite;
    wire [3:0] alucontrol;
    wire branch;
    wire memwrite;
    wire memread;
    wire pcsrc;
    wire memtoreg;
    wire alusrc;


    //parametros do estado
    parameter IF = 3'b000, //posição instrução
              ID = 3'b001, //leitura
              EX = 3'b010, //execução
              MEM = 3'b011, //leitura memoria
              WB = 3'b100, //escrita
              FIM = 3'b110; //finish


    // //maquina de estados
    reg [2:0] estado;

    initial begin
        $dumpfile("wavefile.vcd");
        $dumpvars;
        estado <= IF;
    end

    clock clock(.clk(clk));
    somapc somapc(.PC(PC), .clk(clk), .pcsrc(pcsrc), .immediate(immediate));
    lerinstrucao lerinstrucao(.instrucao(instrucao), .PC(PC), .clk(clk));
    decodificacao decodificacao(.instrucao(instrucao), .opcode(opcode), .rd(rd), .rs1(rs1), .rs2(rs2), .funct3(funct3), .funct7(funct7), .immediate(immediate), .tipo(tipo), .clk(clk));
    sinaisdecontrole sinaisdecontrole(.tipo(tipo), .regiwrite(regiwrite), .memwrite(memwrite), .memread(memread), .alucontrol(alucontrol), .funct3(funct3), .clk(clk), .branch(branch), .memtoreg(memtoreg), .alusrc(alusrc));
    registradores registradores(.clk(clk), .rs1(rs1), .rs2(rs2), .rd(rd), .readdata1R(readdata1R), .readdata2R(readdata2R), .regiwrite(regiwrite), .memtoreg(memtoreg), .aluresult2(aluresult2), .reddataM(reddataM),.reg0(reg0), .reg1(reg1), .reg2(reg2), .reg3(reg3), .reg4(reg4), .reg5(reg5), .reg6(reg6), .reg7(reg7), .reg8(reg8), .reg9(reg9), .reg10(reg10), .reg11(reg11),.reg12(reg12), .reg13(reg13), .reg14(reg14), .reg15(reg15), .reg16(reg16), .reg17(reg17), .reg18(reg18), .reg19(reg19), .reg20(reg20), .reg21(reg21), .reg22(reg22), .reg23(reg23), .reg24(reg24), .reg25(reg25), .reg26(reg26), .reg27(reg27), .reg28(reg28), .reg29(reg29), .reg30(reg30), .reg31(reg31));
    alu alu(.clk(clk), .readdata1R(readdata1R), .readdata2R(readdata2R), .alusrc(alusrc), .alucontrol(alucontrol), .immediate(immediate), .aluresult1(aluresult1), .aluresult2(aluresult2), .pcsrc(pcsrc), .branch(branch));
    memoria memoria(.clk(clk), .aluresult2(aluresult2), .rs2(rs2), .reddataM(reddataM), .memwrite(memwrite), .memread(memread), .immediate(immediate), .mem0(mem0), .mem1(mem1), .mem2(mem2), .mem3(mem3), .mem4(mem4), .mem5(mem5), .mem6(mem6), .mem7(mem7), .mem8(mem8), .mem9(mem9), .mem10(mem10), .mem11(mem11),.mem12(mem12), .mem13(mem13), .mem14(mem14), .mem15(mem15), .mem16(mem16), .mem17(mem17), .mem18(mem18), .mem19(mem19), .mem20(mem20), .mem21(mem21), .mem22(mem22), .mem23(mem23), .mem24(mem24), .mem25(mem25), .mem26(mem26), .mem27(mem27), .mem28(mem28), .mem29(mem29), .mem30(mem30), .mem31(mem31));


    always @(posedge clk) begin
        case(estado)
        IF : begin
            estado <= ID;
        end
        ID: begin
            if(PC < 7) begin
                estado <= IF;
            end
            else begin
                estado <= FIM;
            end
        end
        FIM : begin
            $finish;
        end
        endcase
     
    end


endmodule

Projeto/wavefile.vcd
$date
	Wed May 31 09:05:44 2023
$end
$version
	Icarus Verilog
$end
$timescale
	1s
$end
$scope module main $end
$var wire 3 ! tipo [2:0] $end
$var wire 5 " rs2 [4:0] $end
$var wire 5 # rs1 [4:0] $end
$var wire 1 $ regiwrite $end
$var wire 32 % reg9 [31:0] $end
$var wire 32 & reg8 [31:0] $end
$var wire 32 ' reg7 [31:0] $end
$var wire 32 ( reg6 [31:0] $end
$var wire 32 ) reg5 [31:0] $end
$var wire 32 * reg4 [31:0] $end
$var wire 32 + reg31 [31:0] $end
$var wire 32 , reg30 [31:0] $end
$var wire 32 - reg3 [31:0] $end
$var wire 32 . reg29 [31:0] $end
$var wire 32 / reg28 [31:0] $end
$var wire 32 0 reg27 [31:0] $end
$var wire 32 1 reg26 [31:0] $end
$var wire 32 2 reg25 [31:0] $end
$var wire 32 3 reg24 [31:0] $end
$var wire 32 4 reg23 [31:0] $end
$var wire 32 5 reg22 [31:0] $end
$var wire 32 6 reg21 [31:0] $end
$var wire 32 7 reg20 [31:0] $end
$var wire 32 8 reg2 [31:0] $end
$var wire 32 9 reg19 [31:0] $end
$var wire 32 : reg18 [31:0] $end
$var wire 32 ; reg17 [31:0] $end
$var wire 32 < reg16 [31:0] $end
$var wire 32 = reg15 [31:0] $end
$var wire 32 > reg14 [31:0] $end
$var wire 32 ? reg13 [31:0] $end
$var wire 32 @ reg12 [31:0] $end
$var wire 32 A reg11 [31:0] $end
$var wire 32 B reg10 [31:0] $end
$var wire 32 C reg1 [31:0] $end
$var wire 32 D reg0 [31:0] $end
$var wire 32 E reddataM [31:0] $end
$var wire 32 F readdata2R [31:0] $end
$var wire 32 G readdata1R [31:0] $end
$var wire 5 H rd [4:0] $end
$var wire 1 I pcsrc $end
$var wire 7 J opcode [6:0] $end
$var wire 1 K memwrite $end
$var wire 1 L memtoreg $end
$var wire 1 M memread $end
$var wire 32 N mem9 [31:0] $end
$var wire 32 O mem8 [31:0] $end
$var wire 32 P mem7 [31:0] $end
$var wire 32 Q mem6 [31:0] $end
$var wire 32 R mem5 [31:0] $end
$var wire 32 S mem4 [31:0] $end
$var wire 32 T mem31 [31:0] $end
$var wire 32 U mem30 [31:0] $end
$var wire 32 V mem3 [31:0] $end
$var wire 32 W mem29 [31:0] $end
$var wire 32 X mem28 [31:0] $end
$var wire 32 Y mem27 [31:0] $end
$var wire 32 Z mem26 [31:0] $end
$var wire 32 [ mem25 [31:0] $end
$var wire 32 \ mem24 [31:0] $end
$var wire 32 ] mem23 [31:0] $end
$var wire 32 ^ mem22 [31:0] $end
$var wire 32 _ mem21 [31:0] $end
$var wire 32 ` mem20 [31:0] $end
$var wire 32 a mem2 [31:0] $end
$var wire 32 b mem19 [31:0] $end
$var wire 32 c mem18 [31:0] $end
$var wire 32 d mem17 [31:0] $end
$var wire 32 e mem16 [31:0] $end
$var wire 32 f mem15 [31:0] $end
$var wire 32 g mem14 [31:0] $end
$var wire 32 h mem13 [31:0] $end
$var wire 32 i mem12 [31:0] $end
$var wire 32 j mem11 [31:0] $end
$var wire 32 k mem10 [31:0] $end
$var wire 32 l mem1 [31:0] $end
$var wire 32 m mem0 [31:0] $end
$var wire 32 n instrucao [31:0] $end
$var wire 12 o immediate [11:0] $end
$var wire 7 p funct7 [6:0] $end
$var wire 3 q funct3 [2:0] $end
$var wire 1 r clk $end
$var wire 1 s branch $end
$var wire 1 t alusrc $end
$var wire 32 u aluresult2 [31:0] $end
$var wire 32 v aluresult1 [31:0] $end
$var wire 4 w alucontrol [3:0] $end
$var wire 32 x PC [31:0] $end
$var reg 3 y estado [2:0] $end
$scope module alu $end
$var wire 32 z readdata2R [31:0] $end
$var wire 32 { readdata1R [31:0] $end
$var wire 12 | immediate [11:0] $end
$var wire 1 r clk $end
$var wire 1 s branch $end
$var wire 1 t alusrc $end
$var wire 4 } alucontrol [3:0] $end
$var reg 32 ~ aluresult1 [31:0] $end
$var reg 32 !" aluresult2 [31:0] $end
$var reg 1 I pcsrc $end
$upscope $end
$scope module clock $end
$var reg 1 r clk $end
$upscope $end
$scope module decodificacao $end
$var wire 1 r clk $end
$var wire 32 "" instrucao [31:0] $end
$var reg 3 #" funct3 [2:0] $end
$var reg 7 $" funct7 [6:0] $end
$var reg 12 %" immediate [11:0] $end
$var reg 7 &" opcode [6:0] $end
$var reg 5 '" rd [4:0] $end
$var reg 5 (" rs1 [4:0] $end
$var reg 5 )" rs2 [4:0] $end
$var reg 3 *" tipo [2:0] $end
$upscope $end
$scope module lerinstrucao $end
$var wire 1 r clk $end
$var wire 32 +" PC [31:0] $end
$var reg 32 ," instrucao [31:0] $end
$upscope $end
$scope module memoria $end
$var wire 32 -" aluresult2 [31:0] $end
$var wire 1 r clk $end
$var wire 12 ." immediate [11:0] $end
$var wire 5 /" rs2 [4:0] $end
$var wire 1 K memwrite $end
$var wire 1 M memread $end
$var reg 32 0" mem0 [31:0] $end
$var reg 32 1" mem1 [31:0] $end
$var reg 32 2" mem10 [31:0] $end
$var reg 32 3" mem11 [31:0] $end
$var reg 32 4" mem12 [31:0] $end
$var reg 32 5" mem13 [31:0] $end
$var reg 32 6" mem14 [31:0] $end
$var reg 32 7" mem15 [31:0] $end
$var reg 32 8" mem16 [31:0] $end
$var reg 32 9" mem17 [31:0] $end
$var reg 32 :" mem18 [31:0] $end
$var reg 32 ;" mem19 [31:0] $end
$var reg 32 <" mem2 [31:0] $end
$var reg 32 =" mem20 [31:0] $end
$var reg 32 >" mem21 [31:0] $end
$var reg 32 ?" mem22 [31:0] $end
$var reg 32 @" mem23 [31:0] $end
$var reg 32 A" mem24 [31:0] $end
$var reg 32 B" mem25 [31:0] $end
$var reg 32 C" mem26 [31:0] $end
$var reg 32 D" mem27 [31:0] $end
$var reg 32 E" mem28 [31:0] $end
$var reg 32 F" mem29 [31:0] $end
$var reg 32 G" mem3 [31:0] $end
$var reg 32 H" mem30 [31:0] $end
$var reg 32 I" mem31 [31:0] $end
$var reg 32 J" mem4 [31:0] $end
$var reg 32 K" mem5 [31:0] $end
$var reg 32 L" mem6 [31:0] $end
$var reg 32 M" mem7 [31:0] $end
$var reg 32 N" mem8 [31:0] $end
$var reg 32 O" mem9 [31:0] $end
$var reg 32 P" reddataM [31:0] $end
$upscope $end
$scope module registradores $end
$var wire 32 Q" aluresult2 [31:0] $end
$var wire 1 r clk $end
$var wire 5 R" rd [4:0] $end
$var wire 32 S" reddataM [31:0] $end
$var wire 5 T" rs1 [4:0] $end
$var wire 5 U" rs2 [4:0] $end
$var wire 1 $ regiwrite $end
$var wire 1 L memtoreg $end
$var reg 32 V" readdata1R [31:0] $end
$var reg 32 W" readdata2R [31:0] $end
$var reg 32 X" reg0 [31:0] $end
$var reg 32 Y" reg1 [31:0] $end
$var reg 32 Z" reg10 [31:0] $end
$var reg 32 [" reg11 [31:0] $end
$var reg 32 \" reg12 [31:0] $end
$var reg 32 ]" reg13 [31:0] $end
$var reg 32 ^" reg14 [31:0] $end
$var reg 32 _" reg15 [31:0] $end
$var reg 32 `" reg16 [31:0] $end
$var reg 32 a" reg17 [31:0] $end
$var reg 32 b" reg18 [31:0] $end
$var reg 32 c" reg19 [31:0] $end
$var reg 32 d" reg2 [31:0] $end
$var reg 32 e" reg20 [31:0] $end
$var reg 32 f" reg21 [31:0] $end
$var reg 32 g" reg22 [31:0] $end
$var reg 32 h" reg23 [31:0] $end
$var reg 32 i" reg24 [31:0] $end
$var reg 32 j" reg25 [31:0] $end
$var reg 32 k" reg26 [31:0] $end
$var reg 32 l" reg27 [31:0] $end
$var reg 32 m" reg28 [31:0] $end
$var reg 32 n" reg29 [31:0] $end
$var reg 32 o" reg3 [31:0] $end
$var reg 32 p" reg30 [31:0] $end
$var reg 32 q" reg31 [31:0] $end
$var reg 32 r" reg4 [31:0] $end
$var reg 32 s" reg5 [31:0] $end
$var reg 32 t" reg6 [31:0] $end
$var reg 32 u" reg7 [31:0] $end
$var reg 32 v" reg8 [31:0] $end
$var reg 32 w" reg9 [31:0] $end
$upscope $end
$scope module sinaisdecontrole $end
$var wire 1 r clk $end
$var wire 3 x" funct3 [2:0] $end
$var wire 3 y" tipo [2:0] $end
$var reg 4 z" alucontrol [3:0] $end
$var reg 2 {" aluop [1:0] $end
$var reg 1 t alusrc $end
$var reg 1 s branch $end
$var reg 1 M memread $end
$var reg 1 L memtoreg $end
$var reg 1 K memwrite $end
$var reg 1 $ regiwrite $end
$upscope $end
$scope module somapc $end
$var wire 1 r clk $end
$var wire 12 |" immediate [11:0] $end
$var wire 1 I pcsrc $end
$var reg 32 }" PC [31:0] $end
$upscope $end
$upscope $end
$enddefinitions $end
#0
$dumpvars
b0 }"
bx |"
bx {"
bx z"
bx y"
bx x"
b0 w"
b0 v"
b0 u"
b0 t"
b0 s"
b0 r"
b0 q"
b0 p"
b0 o"
b0 n"
b0 m"
b0 l"
b0 k"
b0 j"
b0 i"
b0 h"
b0 g"
b0 f"
b0 e"
b0 d"
b0 c"
b0 b"
b0 a"
b0 `"
b0 _"
b0 ^"
b0 ]"
b0 \"
b0 ["
b0 Z"
b111 Y"
b0 X"
bx W"
bx V"
bx U"
bx T"
bx S"
bx R"
bx Q"
bx P"
b0 O"
b0 N"
b0 M"
b0 L"
b0 K"
b0 J"
b0 I"
b0 H"
b0 G"
b0 F"
b0 E"
b0 D"
b0 C"
b0 B"
b0 A"
b0 @"
b0 ?"
b0 >"
b0 ="
b0 <"
b0 ;"
b0 :"
b0 9"
b0 8"
b0 7"
b0 6"
b0 5"
b0 4"
b0 3"
b0 2"
b111 1"
b0 0"
bx /"
bx ."
bx -"
bx ,"
b0 +"
bx *"
bx )"
bx ("
bx '"
bx &"
bx %"
bx $"
bx #"
bx ""
bx !"
bx ~
bx }
bx |
bx {
bx z
b0 y
b0 x
bx w
bx v
bx u
xt
xs
0r
bx q
bx p
bx o
bx n
b0 m
b111 l
b0 k
b0 j
b0 i
b0 h
b0 g
b0 f
b0 e
b0 d
b0 c
b0 b
b0 a
b0 `
b0 _
b0 ^
b0 ]
b0 \
b0 [
b0 Z
b0 Y
b0 X
b0 W
b0 V
b0 U
b0 T
b0 S
b0 R
b0 Q
b0 P
b0 O
b0 N
xM
xL
xK
bx J
xI
bx H
bx G
bx F
bx E
b0 D
b111 C
b0 B
b0 A
b0 @
b0 ?
b0 >
b0 =
b0 <
b0 ;
b0 :
b0 9
b0 8
b0 7
b0 6
b0 5
b0 4
b0 3
b0 2
b0 1
b0 0
b0 /
b0 .
b0 -
b0 ,
b0 +
b0 *
b0 )
b0 (
b0 '
b0 &
b0 %
x$
bx #
bx "
bx !
$end
#1
b1 y
1r
#3
0r
#5
b0 y
1r
#7
0r
#9
b1 y
1r
#11
0r
b1 x
b1 +"
b1 }"
b1100001010000000000011 n
b1100001010000000000011 ""
b1100001010000000000011 ,"
#13
b0 y
b11 J
b11 &"
1r
#15
0r
#17
b0 !
b0 *"
b0 y"
b11 o
b11 |
b11 %"
b11 ."
b11 |"
b10 q
b10 #"
b10 x"
b1 #
b1 ("
b1 T"
b0 H
b0 '"
b0 R"
b1 y
1r
#19
0r
#21
b0 y
b111 G
b111 {
b111 V"
1t
1L
0s
b10 w
b10 }
b10 z"
1M
0K
1$
1r
#23
0r
b1000011010001000100011 n
b1000011010001000100011 ""
b1000011010001000100011 ,"
b10 x
b10 +"
b10 }"
#25
b10 o
b10 |
b10 %"
b10 ."
b10 |"
b11 #
b11 ("
b11 T"
b100 H
b100 '"
b100 R"
b100011 J
b100011 &"
0I
b0 v
b0 ~
b1010 u
b1010 !"
b1010 -"
b1010 Q"
b1 y
1r
#27
0r
#29
b0 y
b0 E
b0 P"
b0 S"
b1001 u
b1001 !"
b1001 -"
b1001 Q"
bx D
bx X"
b0 G
b0 {
b0 V"
b10 !
b10 *"
b10 y"
b10 "
b10 )"
b10 /"
b10 U"
b100 o
b100 |
b100 %"
b100 ."
b100 |"
1r
#31
0r
#33
0M
1K
0$
bx *
bx r"
b0 F
b0 z
b0 W"
b100 u
b100 !"
b100 -"
b100 Q"
b1 y
1r
#35
0r
b11 x
b11 +"
b11 }"
b1000000010100101000001010110011 n
b1000000010100101000001010110011 ""
b1000000010100101000001010110011 ,"
#37
b0 y
b0 *
b0 r"
b0 q
b0 #"
b0 x"
b101 "
b101 )"
b101 /"
b101 U"
b101 #
b101 ("
b101 T"
b10000000101 o
b10000000101 |
b10000000101 %"
b10000000101 ."
b10000000101 |"
b110011 J
b110011 &"
1r
#39
0r
#41
b11 !
b11 *"
b11 y"
b101 H
b101 '"
b101 R"
b100000 p
b100000 $"
b10000000101 u
b10000000101 !"
b10000000101 -"
b10000000101 Q"
b10 S
b10 J"
b1 y
1r
#43
0r
#45
b0 y
b101 S
b101 J"
0t
0L
b110 w
b110 }
b110 z"
0K
1$
1r
#47
0r
b11000110100001100110011 n
b11000110100001100110011 ""
b11000110100001100110011 ,"
b100 x
b100 +"
b100 }"
#49
b100 q
b100 #"
b100 x"
b110 H
b110 '"
b110 R"
b110 #
b110 ("
b110 T"
b110 "
b110 )"
b110 /"
b110 U"
b0 p
b0 $"
b0 u
b0 !"
b0 -"
b0 Q"
b1 y
1r
#51
0r
#53
b0 y
b10000000101 )
b10000000101 s"
b10 w
b10 }
b10 z"
1r
#55
0r
#57
b1 y
1r
#59
0r
b101 x
b101 +"
b101 }"
b101000101000001010010011 n
b101000101000001010010011 ""
b101000101000001010010011 ,"
#61
b0 y
b0 q
b0 #"
b0 x"
b101 H
b101 '"
b101 R"
b101 #
b101 ("
b101 T"
b1010 "
b1010 )"
b1010 /"
b1010 U"
b10011 J
b10011 &"
1r
#63
0r
