Projeto/modulos/controle.v
module controle (tipo, regiwrite, aluop, memwrite, memread, alucontrol, funct3, clk, branch, memtoreg, alusrc);
    input wire [2:0] tipo;
    input wire [2:0] funct3;
    //input wire aluresult1;
    input wire clk;
    output reg regiwrite;
    output reg [1:0] aluop;
    output reg memwrite;
    output reg memread;
    output reg [3:0] alucontrol;
    output reg branch;
    output reg memtoreg;
    output reg alusrc;

    always @(posedge clk)begin
        case (tipo)
            3'b000: begin //lw
                regiwrite <= 1'b1;
                aluop <= 2'b00;
                memwrite <= 1'b0;
                memread <= 1'b1;
                alucontrol <= 4'b0010;
                branch <= 1'b0;
                memtoreg <= 1'b1;
                alusrc <= 1'b1;
            end
            3'b010: begin //sw
                regiwrite <= 1'b0;
                aluop <= 2'b00;
                memwrite <= 1'b1;
                memread <= 1'b0;
                alucontrol <= 4'b0010;
                branch <= 1'b0;
                memtoreg <= 1'b1;
                alusrc <= 1'b1;
            end
            3'b011: begin
                case (funct3)
                    3'b000 : begin //sub
                        regiwrite <= 1'b1;
                        aluop <= 2'b10;
                        memwrite <= 1'b0;
                        memread <= 1'b0;
                        alucontrol <= 4'b0110;
                        branch <= 1'b0;
                        memtoreg <= 1'b0;
                        alusrc <= 1'b0;
                    end
                    3'b100 : begin //xor
                        regiwrite <= 1'b1;
                        aluop <= 2'b10;
                        memwrite <= 1'b0;
                        memread <= 1'b0;
                        alucontrol <= 4'b0010;
                        branch <= 1'b0;
                        memtoreg <= 1'b0;
                        alusrc <= 1'b0;
                    end
                    3'b101 : begin //srl
                        regiwrite <= 1'b1;
                        aluop <= 2'b10;
                        memwrite <= 1'b0;
                        memread <= 1'b0;
                        alucontrol <= 4'b0101;
                        branch <= 1'b0;
                        memtoreg <= 1'b0;
                        alusrc <= 1'b0;
                    end
                endcase
            end
            3'b110: begin //beq
                regiwrite <= 1'b0;
                aluop <= 2'b01;
                memwrite <= 1'b0;
                memread <= 1'b0;
                alucontrol <= 4'b0110;
                branch <= 1'b1;
                memtoreg <= 1'b0;
                alusrc <= 1'b1;
            end
        endcase
    end
    
endmodule

Projeto/modulos/decodificacao.v
module decodificacao (instrucao, opcode, rd, rs1, rs2, funct3, funct7, immediate, tipo, clk);
    //input wire clock,
    input wire [31:0] instrucao;
    input wire clk;
    output reg [6:0] opcode;
    output reg [4:0] rd;
    output reg [4:0] rs1;
    output reg [4:0] rs2;
    output reg [2:0] funct3;
    output reg [6:0] funct7;
    output reg [11:0] immediate; 
    output reg [2:0] tipo;

    always @(posedge clk) begin
    opcode <= instrucao [6:0];
    case (opcode[6:4]) 
      3'b000: begin //formato i
        rd <= instrucao[11:7];
        rs1 <= instrucao[19:15];
        funct3 <= instrucao[14:12];
        immediate <= instrucao[31:20];
        tipo <= 3'b000;
      end
      3'b010: begin //formato s
        immediate <= {instrucao[31:25], instrucao[11:7]};
        rs1 <= instrucao[19:15];
        rs2 <= instrucao[24:20];
        funct3 <= instrucao[14:12];
        tipo <= 3'b010;
      end
      3'b011: begin //formato r
        funct7 <= instrucao[31:25];
        rs2 <= instrucao[24:20];
        rs1 <= instrucao[19:15];
        rd <= instrucao[11:7];
        funct3 <= instrucao[14:12];
        tipo <= 3'b011;
      end 
      3'b110: begin //formato sb
        immediate <= {instrucao[31:25], instrucao[11:7]};
        rs1 <= instrucao[19:15];
        rs2 <= instrucao[24:20];
        funct3 <= instrucao[14:12];
        tipo <= 3'b110;
      end 
    endcase
  end

endmodule

Projeto/modulos/lerinstrucao.v
module lerinstrucao (instrucao, PC, clk);
    input wire [31:0] PC;
    input wire clk;
    output reg [31:0] instrucao;
    reg [31:0] instrucoes [0:6]; // Memória de instruções

    initial begin
        $readmemb("entrada/teste.bin", instrucoes); // Lendo instruções em formato binário
        instrucao <= instrucoes[PC];
    end

    always @(posedge clk) begin
        instrucao <= instrucoes[PC];
    end


endmodule

Projeto/modulos/pc.v
module pc (PC, clk);
  input wire clk;
  output reg [31:0] PC;

  initial begin
      PC <= 0;
  end

  always @(posedge clk) begin
      PC <= PC + 1;
  end

endmodule

Projeto/modulos/clock.v
module clock (clk);
    output reg clk;

    initial begin
        clk = 1'b0;
    end

    // Clock
    always begin
        case (clk)
            1'b0: #1 clk <= 1'b1;
            1'b1: #1 clk <= 1'b0;
        endcase
    end

endmodule

Projeto/main.v
`include "modulos/lerinstrucao.v"
`include "modulos/decodificacao.v"
`include "modulos/controle.v"
`include "modulos/pc.v"
`include "modulos/clock.v"

//lw sw sub xor addi srl beq

module main;
    //IF
    wire [31:0] instrucao;
    wire [6:0] opcode;
    wire [4:0] rd;
    wire [4:0] rs1;
    wire [4:0] rs2;
    wire [2:0] funct3;
    wire [6:0] funct7;
    wire [11:0] immediate;
    wire [2:0] tipo;
    wire [31:0] PC;
    wire clk;

    //ID
    wire [31:0] readdata1R; //R para indicar que pertence ao banco de registradores
    wire [31:0] readdata2R; //R para indicar que pertence ao banco de registradores
    wire [31:0] writedata;

    //EX
    wire [31:0] aluresult1;
    wire [31:0] aluresult2;

    //MEM
    wire [31:0] reddataM; //M para indicar que pertence a memoria

    //sinais de controle
    wire regiwrite;
    wire [1:0] aluop;
    wire [3:0] alucontrol;
    wire branch;
    wire memwrite;
    wire memread;
    wire pcsrc;
    wire memtoreg;
    wire alusrc;


    //parametros do estado
    parameter IF = 3'b000, //posição instrução
              ID = 3'b001, //leitura
              EX = 3'b010, //execução
              MEM = 3'b011, //leitura memoria
              WB = 3'b100, //escrita
              FIM = 3'b110; //finish


    // //maquina de estados
    reg [2:0] estado;

    initial begin
        $dumpfile("wavefile.vcd");
        $dumpvars;

        estado <= IF;
    end

    clock geraclk(.clk(clk));
    pc somapc(.PC(PC), .clk(clk));
    lerinstrucao leitura(.instrucao(instrucao), .PC(PC), .clk(clk));
    decodificacao decodificar(.instrucao(instrucao), .opcode(opcode), .rd(rd), .rs1(rs1), .rs2(rs2), .funct3(funct3), .funct7(funct7), .immediate(immediate), .tipo(tipo), .clk(clk));
    controle controlador(.tipo(tipo), .regiwrite(regiwrite), .aluop(aluop), .memwrite(memwrite), .memread(memread), .alucontrol(alucontrol), .funct3(funct3), .clk(clk), .branch(branch), .memtoreg(memtoreg), .alusrc(alusrc));

    always @(posedge clk) begin
        case(estado)
        IF : begin
            estado <= ID;
        end
        ID: begin
            if(PC < 7) begin
                estado <= IF;
            end
            else begin
                estado <= FIM;
            end
        end
        FIM : begin
            $finish;
        end
        endcase
     
    end


endmodule

Projeto/wavefile.vcd
$date
	Mon May 29 20:38:22 2023
$end
$version
	Icarus Verilog
$end
$timescale
	1s
$end
$scope module main $end
$var wire 3 ! tipo [2:0] $end
$var wire 5 " rs2 [4:0] $end
$var wire 5 # rs1 [4:0] $end
$var wire 1 $ regiwrite $end
$var wire 5 % rd [4:0] $end
$var wire 7 & opcode [6:0] $end
$var wire 1 ' memwrite $end
$var wire 1 ( memtoreg $end
$var wire 1 ) memread $end
$var wire 32 * instrucao [31:0] $end
$var wire 12 + immediate [11:0] $end
$var wire 7 , funct7 [6:0] $end
$var wire 3 - funct3 [2:0] $end
$var wire 1 . clk $end
$var wire 1 / branch $end
$var wire 1 0 alusrc $end
$var wire 2 1 aluop [1:0] $end
$var wire 4 2 alucontrol [3:0] $end
$var wire 32 3 PC [31:0] $end
$var reg 3 4 estado [2:0] $end
$scope module controlador $end
$var wire 3 5 tipo [2:0] $end
$var wire 3 6 funct3 [2:0] $end
$var wire 1 . clk $end
$var reg 4 7 alucontrol [3:0] $end
$var reg 2 8 aluop [1:0] $end
$var reg 1 0 alusrc $end
$var reg 1 / branch $end
$var reg 1 ) memread $end
$var reg 1 ( memtoreg $end
$var reg 1 ' memwrite $end
$var reg 1 $ regiwrite $end
$upscope $end
$scope module decodificar $end
$var wire 32 9 instrucao [31:0] $end
$var wire 1 . clk $end
$var reg 3 : funct3 [2:0] $end
$var reg 7 ; funct7 [6:0] $end
$var reg 12 < immediate [11:0] $end
$var reg 7 = opcode [6:0] $end
$var reg 5 > rd [4:0] $end
$var reg 5 ? rs1 [4:0] $end
$var reg 5 @ rs2 [4:0] $end
$var reg 3 A tipo [2:0] $end
$upscope $end
$scope module geraclk $end
$var reg 1 . clk $end
$upscope $end
$scope module leitura $end
$var wire 1 . clk $end
$var wire 32 B PC [31:0] $end
$var reg 32 C instrucao [31:0] $end
$upscope $end
$scope module somapc $end
$var wire 1 . clk $end
$var reg 32 D PC [31:0] $end
$upscope $end
$upscope $end
$enddefinitions $end
#0
$dumpvars
b0 D
bx C
b0 B
bx A
bx @
bx ?
bx >
bx =
bx <
bx ;
bx :
bx 9
bx 8
bx 7
bx 6
bx 5
b0 4
b0 3
bx 2
bx 1
x0
x/
0.
bx -
bx ,
bx +
bx *
x)
x(
x'
bx &
bx %
x$
bx #
bx "
bx !
$end
#1
b1 3
b1 B
b1 D
b110000011010000010000011 *
b110000011010000010000011 9
b110000011010000010000011 C
b1 4
1.
#3
0.
#5
b0 4
b11 &
b11 =
b100011010011000100011 *
b100011010011000100011 9
b100011010011000100011 C
b10 3
b10 B
b10 D
1.
#7
0.
#9
b11 3
b11 B
b11 D
b1000000011000110000001010110011 *
b1000000011000110000001010110011 9
b1000000011000110000001010110011 C
b0 !
b0 5
b0 A
b1 +
b1 <
b10 -
b10 6
b10 :
b11 #
b11 ?
b1100 %
b1100 >
b100011 &
b100011 =
b1 4
1.
#11
0.
#13
b0 4
10
1(
0/
b10 2
b10 7
1)
0'
b0 1
b0 8
1$
b10 !
b10 5
b10 A
b0 -
b0 6
b0 :
b110 "
b110 @
b110 #
b110 ?
b10000000101 +
b10000000101 <
b110011 &
b110011 =
b10100101100001010110011 *
b10100101100001010110011 9
b10100101100001010110011 C
b100 3
b100 B
b100 D
1.
#15
0.
#17
b101 3
b101 B
b101 D
b101000011000000110010011 *
b101000011000000110010011 9
b101000011000000110010011 C
b11 !
b11 5
b11 A
b100 -
b100 6
b100 :
b101 %
b101 >
b101 #
b101 ?
b101 "
b101 @
b0 ,
b0 ;
0)
1'
0$
b1 4
1.
#19
0.
#21
b0 4
00
0(
0'
b10 1
b10 8
1$
b0 -
b0 6
b0 :
b11 %
b11 >
b11 #
b11 ?
b1010 "
b1010 @
b10011 &
b10011 =
b1100110101000110110011 *
b1100110101000110110011 9
b1100110101000110110011 C
b110 3
b110 B
b110 D
1.
#23
0.
#25
b111 3
b111 B
b111 D
b11111110010100011000100011100011 *
b11111110010100011000100011100011 9
b11111110010100011000100011100011 C
b110011 &
b110011 =
b110 2
b110 7
b1 4
1.
#27
0.
#29
b110 4
b10001 %
b10001 >
b101 "
b101 @
b1111111 ,
b1111111 ;
b1100011 &
b1100011 =
bx *
bx 9
bx C
b1000 3
b1000 B
b1000 D
1.
#31
0.
#33
b1001 3
b1001 B
b1001 D
b110 !
b110 5
b110 A
bx -
bx 6
bx :
bx "
bx @
bx #
bx ?
bx +
bx <
bx &
bx =
1.
